autoclr/README.md
autoclr/__init__.py
autoclr/loaders/__init__.py
autoclr/loaders/default.py
autoclr/loaders/offline.py
autoclr/loaders/online.py
autoclr/loaders/system.py
autoclr-1.0.0.dist-info/LICENSE
autoclr-1.0.0.dist-info/WHEEL
autoclr-1.0.0.dist-info/METADATA
autoclr-1.0.0.dist-info/RECORD
