Metadata-Version: 2.3
Name: autoclr
Version: 1.0.0
Summary: Automatic loader for pythonnet(coreclr)
Author-email: somehitDev <this.dev.somehit@gmail.com>
Requires-Python: >=3.7
Classifier: License :: OSI Approved :: MIT License
Classifier: Development Status :: 2 - Pre-Alpha
Classifier: Intended Audience :: Developers
Classifier: Operating System :: POSIX
Classifier: Operating System :: MacOS :: MacOS X
Classifier: Operating System :: Microsoft :: Windows
Classifier: Programming Language :: Python :: 3
Classifier: Programming Language :: Python :: 3.7
Classifier: Programming Language :: Python :: 3.8
Classifier: Programming Language :: Python :: 3.9
Classifier: Programming Language :: Python :: 3.10
Classifier: Programming Language :: Python :: 3.11
Classifier: Programming Language :: Python :: 3.12
Classifier: Programming Language :: Python :: 3.13
Requires-Dist: pythonnet==3.0.5
Requires-Dist: wget==3.2
Project-URL: Repository, https://github.com/somehitDev/autoclr
